autosar/__init__.py
autosar/ar_object.py
autosar/base.py
autosar/behavior.py
autosar/builder.py
autosar/collection.py
autosar/component.py
autosar/constant.py
autosar/data_transformation.py
autosar/datatype.py
autosar/ecu.py
autosar/element.py
autosar/ethernet_cluster.py
autosar/has_logger.py
autosar/mode.py
autosar/package.py
autosar/pdu.py
autosar/port.py
autosar/portinterface.py
autosar/service_instance_collection.py
autosar/signal.py
autosar/some_ip_tp.py
autosar/swc_implementation.py
autosar/system.py
autosar/workspace.py
autosar/extractor/__init__.py
autosar/extractor/common.py
autosar/extractor/data_type_extractor.py
autosar/extractor/e2e.py
autosar/extractor/parse_arxml.py
autosar/extractor/system_extractor.py
autosar/parser/__init__.py
autosar/parser/behavior_parser.py
autosar/parser/collection_parser.py
autosar/parser/component_parser.py
autosar/parser/constant_parser.py
autosar/parser/data_transformation_parser.py
autosar/parser/datatype_parser.py
autosar/parser/ecu_parser.py
autosar/parser/ethernet_cluster_parser.py
autosar/parser/mode_parser.py
autosar/parser/package_parser.py
autosar/parser/parser_base.py
autosar/parser/pdu_parser.py
autosar/parser/portinterface_parser.py
autosar/parser/service_instance_collection_parser.py
autosar/parser/signal_parser.py
autosar/parser/some_ip_tp_parser.py
autosar/parser/swc_implementation_parser.py
autosar/parser/system_parser.py
arxml-0.4.0.dist-info/LICENSE
arxml-0.4.0.dist-info/METADATA
arxml-0.4.0.dist-info/WHEEL
arxml-0.4.0.dist-info/top_level.txt
arxml-0.4.0.dist-info/RECORD
