Metadata-Version: 2.1
Name: arxml
Version: 0.4.0
Summary: Python AUTOSAR XML parser
License: The MIT License (MIT)
Requires-Python: >=3.11
License-File: LICENSE
